hatch_test_quasrahub/__about__.py
hatch_test_quasrahub/__init__.py
hatch_test_quasrahub-0.1.0.dist-info/METADATA
hatch_test_quasrahub-0.1.0.dist-info/WHEEL
hatch_test_quasrahub-0.1.0.dist-info/licenses/LICENSE.txt
hatch_test_quasrahub-0.1.0.dist-info/RECORD
