Metadata-Version: 2.1
Name: hatch-test-quasrahub
Version: 0.1.0
Project-URL: Documentation, https://github.com/unknown/hatch-test-quasrahub#readme
Project-URL: Issues, https://github.com/unknown/hatch-test-quasrahub/issues
Project-URL: Source, https://github.com/unknown/hatch-test-quasrahub
Author-email: Youngjin Jo <yjinjo@berkeley.edu>
License-Expression: MIT
License-File: LICENSE.txt
Classifier: Development Status :: 4 - Beta
Classifier: Programming Language :: Python
Classifier: Programming Language :: Python :: 3.7
Classifier: Programming Language :: Python :: 3.8
Classifier: Programming Language :: Python :: 3.9
Classifier: Programming Language :: Python :: 3.10
Classifier: Programming Language :: Python :: 3.11
Classifier: Programming Language :: Python :: Implementation :: CPython
Classifier: Programming Language :: Python :: Implementation :: PyPy
Requires-Python: >=3.7
